royalur/__init__.py
royalur/game.py
royalur/model/__init__.py
royalur/model/board.py
royalur/model/dice.py
royalur/model/metadata.py
royalur/model/path.py
royalur/model/player.py
royalur/model/settings.py
royalur/model/shape.py
royalur/model/tile.py
royalur/rules/__init__.py
royalur/rules/rules.py
royalur/rules/simple.py
royalur/rules/state/__init__.py
royalur/rules/state/action.py
royalur/rules/state/playable.py
royalur/rules/state/state.py
test/__init__.py
test/__main__.py
test/test_example.py
test/test_random_games.py
RoyalUr-0.0.6.dist-info/LICENSE
RoyalUr-0.0.6.dist-info/METADATA
RoyalUr-0.0.6.dist-info/WHEEL
RoyalUr-0.0.6.dist-info/top_level.txt
RoyalUr-0.0.6.dist-info/zip-safe
RoyalUr-0.0.6.dist-info/RECORD
