Metadata-Version: 2.1
Name: RoyalUr
Version: 0.0.6
Summary: An API to support the playing and analysis of games of The Royal Game of Ur.
Home-page: https://github.com/RoyalUr/RoyalUr-Python
Author: Padraig Lamont
Author-email: padraiglamont@gmail.com
License: MIT License
Keywords: game,boardgame
Classifier: Topic :: Games/Entertainment :: Board Games
License-File: LICENSE
Requires-Dist: overrides >=7.4.0
